oore.py
oore-0.2.1.dist-info/DESCRIPTION.rst
oore-0.2.1.dist-info/METADATA
oore-0.2.1.dist-info/metadata.json
oore-0.2.1.dist-info/RECORD
oore-0.2.1.dist-info/top_level.txt
oore-0.2.1.dist-info/WHEEL
