Metadata-Version: 2.0
Name: oore
Version: 0.2.1
Summary: Object-Oriented Regular Expressions
Home-page: https://github.com/DasIch/oore
Author: Daniel Neuhäuser
Author-email: ich@danielneuhaeuser.de
License: UNKNOWN
Platform: UNKNOWN
Classifier: Intended Audience :: Developers
Classifier: License :: OSI Approved :: BSD License
Classifier: Programming Language :: Python
Classifier: Programming Language :: Python :: 2
Classifier: Programming Language :: Python :: 2.7
Classifier: Programming Language :: Python :: 3
Classifier: Programming Language :: Python :: 3.3
Classifier: Programming Language :: Python :: 3.4
Classifier: Programming Language :: Python :: Implementation :: CPython
Classifier: Programming Language :: Python :: Implementation :: PyPy
